evolutionary_algos/__init__.py
evolutionary_algos-0.0.4.dist-info/LICENSE
evolutionary_algos-0.0.4.dist-info/METADATA
evolutionary_algos-0.0.4.dist-info/WHEEL
evolutionary_algos-0.0.4.dist-info/top_level.txt
evolutionary_algos-0.0.4.dist-info/RECORD
