Metadata-Version: 2.1
Name: evolutionary-algos
Version: 0.0.4
Summary: A small evolutionary neural net
Author-email: Daniel Petersson <bgd.petersson@icloud.com>
License: Copyright (c) 2018 The Python Packaging Authority        
Project-URL: Homepage, https://github.com/DanielPeterssonAI/EvoMLP
Project-URL: Bug Tracker, https://github.com/DanielPeterssonAI/EvoMLP/issues
Classifier: Programming Language :: Python :: 3
Classifier: License :: OSI Approved :: MIT License
Classifier: Operating System :: OS Independent
Requires-Python: >=3.7
License-File: LICENSE
Requires-Dist: numpy
